Workbook

Sheet Trade Book
A1: No | B1: Day | C1: Date | D1: Sell Algo(Angel One) | E1: Brokerage(Angel One) | F1: Other Charges(Angel One) | G1: Total Charges(Angel One) | H1: Final Net(Angel One) | I1: Sell Algo(Mummy) | J1: Brokerage(Mummy) | K1: Other charge | L1: Final Net(Finvasia) | M1: Total Charge(finvasia) | N1: Algos | O1: algo charges | P1: Charges | Q1: Profit | R1: Overall | S1: DD | T1: 50 Avg Profit | U1: 100 Avg Profit | V1: 100 Avg Charge | W1: Charge/Profit Ratio | X1: Capital | Y1: 100 D Avg Capital | Z1: Profit/Capital Ratio(bps)
R2: 0 | S2: 0 | X2: 1200000
A3: 1 | B3: Tuesday | C3: 45748 | I3: =10441-12512 -> -2071 | J3: 1750 | N3: 17 | O3: =ROUNDUP((N3 - 3)*12.5 + 62.5,0) -> 238 | P3: =J3+O3 -> 1988 | Q3: =IF(I3 = "N/A","",SUM(I3)-P3) -> -4059 | R3: =R2+Q3 -> -4059 | S3: =IF(I3 = "N/A","0",R3-MAX($R$1:R3)) -> -4059 | X3: 1200000
A4: =A3+1 -> 2 | B4: Wednesday | C4: 45749 | I4: 6518 | J4: 298 | N4: 8 | O4: =ROUNDUP((N4 - 3)*12.5 + 62.5,0) -> 125 | P4: =J4+O4 -> 423 | Q4: =IF(I4 = "N/A","",SUM(I4)-P4) -> 6095 | R4: =R3+Q4 -> 2036 | S4: =IF(I4 = "N/A","0",R4-MAX($R$1:R4)) -> 0 | X4: 1200000
A5: =A4+1 -> 3 | B5: Thursday | C5: 45750 | I5: 10567 | J5: 130 | N5: 8 | O5: =ROUNDUP((N5 - 3)*12.5 + 62.5,0) -> 125 | P5: =J5+O5 -> 255 | Q5: =IF(I5 = "N/A","",SUM(I5)-P5) -> 10312 | R5: =R4+Q5 -> 12348 | S5: =IF(I5 = "N/A","0",R5-MAX($R$1:R5)) -> 0 | X5: 1200000
A6: =A5+1 -> 4 | B6: Friday | C6: 45751 | I6: =10281-1607 -> 8674 | J6: 310 | N6: 6 | O6: =ROUNDUP((N6 - 3)*12.5 + 62.5,0) -> 100 | P6: =J6+O6 -> 410 | Q6: =IF(I6 = "N/A","",SUM(I6)-P6) -> 8264 | R6: =R5+Q6 -> 20612 | S6: =IF(I6 = "N/A","0",R6-MAX($R$1:R6)) -> 0 | X6: 1200000
A7: =A6+1 -> 5 | B7: Monday | C7: 45754 | I7: 442 | J7: 3110 | N7: 14 | O7: =ROUNDUP((N7 - 3)*12.5 + 62.5,0) -> 200 | P7: =J7+O7 -> 3310 | Q7: =IF(I7 = "N/A","",SUM(I7)-P7) -> -2868 | R7: =R6+Q7 -> 17744 | S7: =IF(I7 = "N/A","0",R7-MAX($R$1:R7)) -> -2868 | X7: 1200000
A8: =A7+1 -> 6 | B8: Tuesday | C8: 45755 | I8: 5773 | J8: 1550 | N8: 15 | O8: =ROUNDUP((N8 - 3)*12.5 + 62.5,0) -> 213 | P8: =J8+O8 -> 1763 | Q8: =IF(I8 = "N/A","",SUM(I8)-P8) -> 4010 | R8: =R7+Q8 -> 21754 | S8: =IF(I8 = "N/A","0",R8-MAX($R$1:R8)) -> 0 | X8: 1200000
A9: =A8+1 -> 7 | B9: Wednesday | C9: 45756 | I9: 13822 | J9: 113 | N9: 6 | O9: =ROUNDUP((N9 - 3)*12.5 + 62.5,0) -> 100 | P9: =J9+O9 -> 213 | Q9: =IF(I9 = "N/A","",SUM(I9)-P9) -> 13609 | R9: =R8+Q9 -> 35363 | S9: =IF(I9 = "N/A","0",R9-MAX($R$1:R9)) -> 0 | X9: 1200000
A10: =A9+1 -> 8 | B10: Thursday | C10: 45757 | I10: N/A | J10: 0 | N10: 8 | O10: =ROUNDUP((N10 - 3)*12.5 + 62.5,0) -> 125 | P10: =J10+O10 -> 125 | Q10: =IF(I10 = "N/A","",SUM(I10)-P10) | R10: =R9+Q10 -> 35363 | S10: =IF(I10 = "N/A","0",R10-MAX($R$1:R10)) -> 0 | X10: 1200000
A11: =A10+1 -> 9 | B11: Friday | C11: 45758 | I11: 6195 | J11: 979 | N11: 8 | O11: =ROUNDUP((N11 - 3)*12.5 + 62.5,0) -> 125 | P11: =J11+O11 -> 1104 | Q11: =IF(I11 = "N/A","",SUM(I11)-P11) -> 5091 | R11: =R10+Q11 -> 40454 | S11: =IF(I11 = "N/A","0",R11-MAX($R$1:R11)) -> 0 | X11: 1200000
A12: =A11+1 -> 10 | B12: Monday | C12: 45761 | I12: N/A | J12: 0 | N12: 8 | O12: =ROUNDUP((N12 - 3)*12.5 + 62.5,0) -> 125 | P12: =J12+O12 -> 125 | Q12: =IF(I12 = "N/A","",SUM(I12)-P12) | R12: =R11+Q12 -> 40454 | S12: =IF(I12 = "N/A","0",R12-MAX($R$1:R12)) -> 0 | X12: 1200000
A13: =A12+1 -> 11 | B13: Tuesday | C13: 45762 | I13: 543 | J13: 190 | N13: 8 | O13: =ROUNDUP((N13 - 3)*12.5 + 62.5,0) -> 125 | P13: =J13+O13 -> 315 | Q13: =IF(I13 = "N/A","",SUM(I13)-P13) -> 228 | R13: =R12+Q13 -> 40682 | S13: =IF(I13 = "N/A","0",R13-MAX($R$1:R13)) -> 0 | X13: 1200000
A14: =A13+1 -> 12 | B14: Wednesday | C14: 45763 | I14: =753-726 -> 27 | J14: =30+380 -> 410 | N14: 8 | O14: =ROUNDUP((N14 - 3)*12.5 + 62.5,0) -> 125 | P14: =J14+O14 -> 535 | Q14: =IF(I14 = "N/A","",SUM(I14)-P14) -> -508 | R14: =R13+Q14 -> 40174 | S14: =IF(I14 = "N/A","0",R14-MAX($R$1:R14)) -> -508 | X14: 1200000
A15: =A14+1 -> 13 | B15: Thursday | C15: 45764 | I15: -13000 | J15: 0 | N15: 11 | O15: =ROUNDUP((N15 - 3)*12.5 + 62.5,0) -> 163 | P15: =J15+O15 -> 163 | Q15: =IF(I15 = "N/A","",SUM(I15)-P15) -> -13163 | R15: =R14+Q15 -> 27011 | S15: =IF(I15 = "N/A","0",R15-MAX($R$1:R15)) -> -13671 | X15: 1200000
A16: =A15+1 -> 14 | B16: Friday | C16: 45765 | I16: 5898 | J16: 198 | N16: 14 | O16: =ROUNDUP((N16 - 3)*12.5 + 62.5,0) -> 200 | P16: =J16+O16 -> 398 | Q16: =IF(I16 = "N/A","",SUM(I16)-P16) -> 5500 | R16: =R15+Q16 -> 32511 | S16: =IF(I16 = "N/A","0",R16-MAX($R$1:R16)) -> -8171 | X16: 1200000
A17: =A16+1 -> 15 | B17: Monday | C17: 45768 | I17: N/A | J17: 160 | N17: 14 | O17: =ROUNDUP((N17 - 3)*12.5 + 62.5,0) -> 200 | P17: =J17+O17 -> 360 | Q17: =IF(I17 = "N/A","",SUM(I17)-P17) | R17: =R16+Q17 -> 32511 | S17: =IF(I18 = "N/A","0",R17-MAX($R$1:R17)) -> -8171 | X17: 1200000
A18: =A17+1 -> 16 | B18: Tuesday | C18: 45769 | I18: 4581 | J18: 3000 | N18: 14 | O18: =ROUNDUP((N18 - 3)*12.5 + 62.5,0) -> 200 | P18: =J18+O18 -> 3200 | Q18: =IF(I18 = "N/A","",SUM(I18)-P18) -> 1381 | R18: =R17+Q18 -> 33892 | S18: =IF(I19 = "N/A","0",R18-MAX($R$1:R18)) -> -6790 | X18: 1200000
A19: =A18+1 -> 17 | B19: Wednesday | C19: 45770 | I19: -13000 | J19: 1000 | N19: 15 | O19: =ROUNDUP((N19 - 3)*12.5 + 62.5,0) -> 213 | P19: =J19+O19 -> 1213 | Q19: =IF(I19 = "N/A","",SUM(I19)-P19) -> -14213 | R19: =R18+Q19 -> 19679 | S19: =IF(I20 = "N/A","0",R19-MAX($R$1:R19)) -> -21003 | X19: 1200000
A20: =A19+1 -> 18 | B20: Thursday | C20: 45771 | I20: -17000 | J20: 0 | N20: 8 | O20: =ROUNDUP((N20 - 3)*12.5 + 62.5,0) -> 125 | P20: =J20+O20 -> 125 | Q20: =IF(I20 = "N/A","",SUM(I20)-P20) -> -17125 | R20: =R19+Q20 -> 2554 | S20: =IF(I289 = "N/A","0",R20-MAX($R$1:R20)) -> -38128 | X20: 1200000
A21: 19 | B21: Monday | C21: 28 Apr 25 | I21: -4852.5 | J21: 226.66 | N21: 8 | O21: =ROUNDUP((N21 - 3)*12.5 + 62.5,0) -> 125 | P21: =ROUND(J21+O21,0) -> 352 | Q21: =IF(I21 = "N/A","",ROUND(SUM(I21)-P21,0)) -> -5205 | R21: =R20+Q21 -> -2651 | S21: =IF(I290 = "N/A","0",R21-MAX($R$1:R21)) -> -43333 | X21: 1200000
A22: 20 | B22: Tuesday | C22: 29 Apr 25 | I22: 763 | J22: 430.03 | N22: 8 | O22: =ROUNDUP((N22 - 3)*12.5 + 62.5,0) -> 125 | P22: =ROUND(J22+O22,0) -> 555 | Q22: =IF(I22 = "N/A","",ROUND(SUM(I22)-P22,0)) -> 208 | R22: =R21+Q22 -> -2443 | S22: =IF(I291 = "N/A","0",R22-MAX($R$1:R22)) -> -43125 | X22: 1200000
A23: 21 | B23: Wednesday | C23: 30 Apr 25 | I23: -6753.75 | J23: 830.17 | N23: 8 | O23: =ROUNDUP((N23 - 3)*12.5 + 62.5,0) -> 125 | P23: =ROUND(J23+O23,0) -> 955 | Q23: =IF(I23 = "N/A","",ROUND(SUM(I23)-P23,0)) -> -7709 | R23: =R22+Q23 -> -10152 | S23: =IF(I292 = "N/A","0",R23-MAX($R$1:R23)) -> -50834 | X23: 1200000
A24: 22 | B24: Friday | C24: 2 May 25 | I24: 4586.25 | J24: 853.7 | N24: 8 | O24: =ROUNDUP((N24 - 3)*12.5 + 62.5,0) -> 125 | P24: =ROUND(J24+O24,0) -> 979 | Q24: =IF(I24 = "N/A","",ROUND(SUM(I24)-P24,0)) -> 3607 | R24: =R23+Q24 -> -6545 | S24: =IF(I293 = "N/A","0",R24-MAX($R$1:R24)) -> -47227 | X24: 1200000
A25: 23 | B25: Monday | C25: 5 May 25 | I25: -3540 | J25: 282.76 | N25: 8 | O25: =ROUNDUP((N25 - 3)*12.5 + 62.5,0) -> 125 | P25: =ROUND(J25+O25,0) -> 408 | Q25: =IF(I25 = "N/A","",ROUND(SUM(I25)-P25,0)) -> -3948 | R25: =R24+Q25 -> -10493 | S25: =IF(I294 = "N/A","0",R25-MAX($R$1:R25)) -> -51175 | X25: 1200000
A26: 24 | B26: Tuesday | C26: 6 May 25 | I26: 5064 | J26: 228.56 | N26: 8 | O26: =ROUNDUP((N26 - 3)*12.5 + 62.5,0) -> 125 | P26: =ROUND(J26+O26,0) -> 354 | Q26: =IF(I26 = "N/A","",ROUND(SUM(I26)-P26,0)) -> 4710 | R26: =R25+Q26 -> -5783 | S26: =IF(I295 = "N/A","0",R26-MAX($R$1:R26)) -> -46465 | X26: 1200000
A27: 25 | B27: Wednesday | C27: 7 May 25 | I27: 3521.25 | J27: 194.5 | N27: 8 | O27: =ROUNDUP((N27 - 3)*12.5 + 62.5,0) -> 125 | P27: =ROUND(J27+O27,0) -> 320 | Q27: =IF(I27 = "N/A","",ROUND(SUM(I27)-P27,0)) -> 3201 | R27: =R26+Q27 -> -2582 | S27: =IF(I296 = "N/A","0",R27-MAX($R$1:R27)) -> -43264 | X27: 1200000
A28: 26 | B28: Thursday | C28: 8 May 25 | I28: 4170 | J28: 369.78 | N28: 8 | O28: =ROUNDUP((N28 - 3)*12.5 + 62.5,0) -> 125 | P28: =ROUND(J28+O28,0) -> 495 | Q28: =IF(I28 = "N/A","",ROUND(SUM(I28)-P28,0)) -> 3675 | R28: =R27+Q28 -> 1093 | S28: =IF(I297 = "N/A","0",R28-MAX($R$1:R28)) -> -39589 | X28: 1200000
A29: 27 | B29: Friday | C29: 9 May 25 | I29: -1496.25 | J29: 757.84 | N29: 8 | O29: =ROUNDUP((N29 - 3)*12.5 + 62.5,0) -> 125 | P29: =ROUND(J29+O29,0) -> 883 | Q29: =IF(I29 = "N/A","",ROUND(SUM(I29)-P29,0)) -> -2379 | R29: =R28+Q29 -> -1286 | S29: =IF(I298 = "N/A","0",R29-MAX($R$1:R29)) -> -41968 | X29: 1200000
A30: 28 | B30: Monday | C30: 12 May 25 | I30: -13657.5 | J30: 936.18 | N30: 16 | O30: =ROUNDUP((N30 - 3)*12.5 + 62.5,0) -> 225 | P30: =ROUND(J30+O30,0) -> 1161 | Q30: =IF(I30 = "N/A","",ROUND(SUM(I30)-P30,0)) -> -14819 | R30: =R29+Q30 -> -16105 | S30: =IF(I299 = "N/A","0",R30-MAX($R$1:R30)) -> -56787 | X30: 1200000
A31: 29 | B31: Tuesday | C31: 13 May 25 | I31: 2742 | J31: 1350.62 | N31: 20 | O31: =ROUNDUP((N31 - 3)*12.5 + 62.5,0) -> 275 | P31: =ROUND(J31+O31,0) -> 1626 | Q31: =IF(I31 = "N/A","",ROUND(SUM(I31)-P31,0)) -> 1116 | R31: =R30+Q31 -> -14989 | S31: =IF(I300 = "N/A","0",R31-MAX($R$1:R31)) -> -55671 | X31: 1200000
A32: 30 | B32: Wednesday | C32: 14 May 25 | I32: 5272.5 | J32: 194 | N32: 20 | O32: =ROUNDUP((N32 - 3)*12.5 + 62.5,0) -> 275 | P32: =ROUND(J32+O32,0) -> 469 | Q32: =IF(I32 = "N/A","",ROUND(SUM(I32)-P32,0)) -> 4804 | R32: =R31+Q32 -> -10185 | S32: =IF(I301 = "N/A","0",R32-MAX($R$1:R32)) -> -50867 | X32: 1200000
... A44: 42 | B44: Thursday | C44: 29 May 25 | I44: -8000 | J44: 0 | N44: 8 | O44: =ROUNDUP((N44 - 3)*12.5 + 62.5,0) -> 125 | P44: =ROUND(J44+O44,0) -> 125 | Q44: =IF(I44 = "N/A","",ROUND(SUM(I44)-P44,0)) -> -8125 | R44: =R43+Q44 -> 25105 | S44: =IF(I313 = "N/A","0",R44-MAX($R$1:R44)) -> -15577 | X44: 1200000
A45: 44 | B45: Friday | C45: 30 May 25 | I45: -8000 | J45: 0 | N45: 8 | O45: =ROUNDUP((N45 - 3)*12.5 + 62.5,0) -> 125 | P45: =ROUND(J45+O45,0) -> 125 | Q45: =IF(I45 = "N/A","",ROUND(SUM(I45)-P45,0)) -> -8125 | R45: =R44+Q45 -> 16980 | S45: =IF(I315 = "N/A","0",R45-MAX($R$1:R45)) -> -23702 | X45: 1200000
A46: 45 | B46: Monday | C46: 2 Jun 25 | I46: 7598 | J46: 716.21 | N46: 8 | O46: =ROUNDUP((N46 - 3)*12.5 + 62.5,0) -> 125 | P46: =ROUND(J46+O46,0) -> 841 | Q46: =IF(I46 = "N/A","",ROUND(SUM(I46)-P46,0)) -> 6757 | R46: =R45+Q46 -> 23737 | S46: =IF(I316 = "N/A","0",R46-MAX($R$1:R46)) -> -16945 | X46: 1200000
A47: 46 | B47: Tuesday | C47: 3 Jun 25 | I47: 5953.5 | J47: 1124.54 | N47: 8 | O47: =ROUNDUP((N47 - 3)*12.5 + 62.5,0) -> 125 | P47: =ROUND(J47+O47,0) -> 1250 | Q47: =IF(I47 = "N/A","",ROUND(SUM(I47)-P47,0)) -> 4704 | R47: =R46+Q47 -> 28441 | S47: =IF(I317 = "N/A","0",R47-MAX($R$1:R47)) -> -12241 | X47: 1200000
A48: 47 | B48: Wednesday | C48: 4 Jun 25 | I48: 1841.25 | J48: 504.7 | N48: 8 | O48: =ROUNDUP((N48 - 3)*12.5 + 62.5,0) -> 125 | P48: =ROUND(J48+O48,0) -> 630 | Q48: =IF(I48 = "N/A","",ROUND(SUM(I48)-P48,0)) -> 1211 | R48: =R47+Q48 -> 29652 | S48: =IF(I318 = "N/A","0",R48-MAX($R$1:R48)) -> -11030 | X48: 1200000
A49: 48 | B49: Thursday | C49: 5 Jun 25 | I49: 1706.25 | J49: 935 | N49: 20 | O49: =ROUNDUP((N49 - 3)*12.5 + 62.5,0) -> 275 | P49: =ROUND(J49+O49,0) -> 1210 | Q49: =IF(I49 = "N/A","",ROUND(SUM(I49)-P49,0)) -> 496 | R49: =R48+Q49 -> 30148 | S49: =IF(I319 = "N/A","0",R49-MAX($R$1:R49)) -> -10534 | X49: 1200000
A50: 49 | B50: Friday | C50: 6 Jun 25 | I50: 2691 | J50: 434.67 | N50: 5 | O50: =ROUNDUP((N50 - 3)*12.5 + 62.5,0) -> 88 | P50: =ROUND(J50+O50,0) -> 523 | Q50: =IF(I50 = "N/A","",ROUND(SUM(I50)-P50,0)) -> 2168 | R50: =R49+Q50 -> 32316 | S50: =IF(I320 = "N/A","0",R50-MAX($R$1:R50)) -> -8366 | X50: 1200000
A51: 50 | B51: Monday | C51: 9 Jun 25 | I51: 8606.25 | J51: 149.47 | N51: 8 | O51: =ROUNDUP((N51 - 3)*12.5 + 62.5,0) -> 125 | P51: =ROUND(J51+O51,0) -> 274 | Q51: =IF(I51 = "N/A","",ROUND(SUM(I51)-P51,0)) -> 8332 | R51: =R50+Q51 -> 40648 | S51: =IF(I321 = "N/A","0",R51-MAX($R$1:R51)) -> -34 | X51: 1200000
A52: 51 | B52: Tuesday | C52: 10 Jun 25 | I52: 20058.5 | J52: 435.34 | N52: 8 | O52: =ROUNDUP((N52 - 3)*12.5 + 62.5,0) -> 125 | P52: =ROUND(J52+O52,0) -> 560 | Q52: =IF(I52 = "N/A","",ROUND(SUM(I52)-P52,0)) -> 19499 | R52: =R51+Q52 -> 60147 | S52: =IF(I322 = "N/A","0",R52-MAX($R$1:R52)) -> 0 | X52: 1200000
A53: 52 | B53: Wednesday | C53: 11 Jun 25 | I53: -3071.25 | J53: 212.42 | N53: 8 | O53: =ROUNDUP((N53 - 3)*12.5 + 62.5,0) -> 125 | P53: =ROUND(J53+O53,0) -> 337 | Q53: =IF(I53 = "N/A","",ROUND(SUM(I53)-P53,0)) -> -3408 | R53: =R52+Q53 -> 56739 | S53: =IF(I323 = "N/A","0",R53-MAX($R$1:R53)) -> -3408 | T53: =ROUND(AVERAGE(Q4:Q53),0) -> 1294 | X53: 1200000
A54: 53 | B54: Thursday | C54: 12 Jun 25 | I54: -4522.5 | J54: 1438.89 | N54: 25 | O54: =ROUNDUP((N54 - 3)*12.5 + 62.5,0) -> 338 | P54: =ROUND(J54+O54,0) -> 1777 | Q54: =IF(I54 = "N/A","",ROUND(SUM(I54)-P54,0)) -> -6300 | R54: =R53+Q54 -> 50439 | S54: =IF(I324 = "N/A","0",R54-MAX($R$1:R54)) -> -9708 | T54: =ROUND(AVERAGE(Q5:Q54),0) -> 1030 | X54: 1200000
A55: 54 | B55: Friday | C55: 13 Jun 25 | I55: 1650.5 | J55: 693.37 | N55: 8 | O55: =ROUNDUP((N55 - 3)*12.5 + 62.5,0) -> 125 | P55: =ROUND(J55+O55,0) -> 818 | Q55: =IF(I55 = "N/A","",ROUND(SUM(I55)-P55,0)) -> 833 | R55: =R54+Q55 -> 51272 | S55: =IF(I325 = "N/A","0",R55-MAX($R$1:R55)) -> -8875 | T55: =ROUND(AVERAGE(Q6:Q55),0) -> 828 | X55: 1200000
A56: 55 | B56: Monday | C56: 16 Jun 25 | I56: -5513.75 | J56: 1074.19 | N56: 15 | O56: =ROUNDUP((N56 - 3)*12.5 + 62.5,0) -> 213 | P56: =ROUND(J56+O56,0) -> 1287 | Q56: =IF(I56 = "N/A","",ROUND(SUM(I56)-P56,0)) -> -6801 | R56: =R55+Q56 -> 44471 | S56: =IF(I326 = "N/A","0",R56-MAX($R$1:R56)) -> -15676 | T56: =ROUND(AVERAGE(Q7:Q56),0) -> 508 | X56: 1200000
A57: 56 | B57: Tuesday | C57: 17 Jun 25 | I57: 17140 | J57: 561.07 | N57: 15 | O57: =ROUNDUP((N57 - 3)*12.5 + 62.5,0) -> 213 | P57: =ROUND(J57+O57,0) -> 774 | Q57: =IF(I57 = "N/A","",ROUND(SUM(I57)-P57,0)) -> 16366 | R57: =R56+Q57 -> 60837 | S57: =IF(I327 = "N/A","0",R57-MAX($R$1:R57)) -> 0 | T57: =ROUND(AVERAGE(Q8:Q57),0) -> 917 | X57: 1200000
A58: 57 | B58: Wednesday | C58: 18 Jun 25 | I58: 3108.75 | J58: 347.52 | N58: 15 | O58: =ROUNDUP((N58 - 3)*12.5 + 62.5,0) -> 213 | P58: =ROUND(J58+O58,0) -> 561 | Q58: =IF(I58 = "N/A","",ROUND(SUM(I58)-P58,0)) -> 2548 | R58: =R57+Q58 -> 63385 | S58: =IF(I328 = "N/A","0",R58-MAX($R$1:R58)) -> 0 | T58: =ROUND(AVERAGE(Q9:Q58),0) -> 886 | X58: 1200000
A59: 58 | B59: Thursday | C59: 19 Jun 25 | I59: 8546.25 | J59: 512.08 | N59: 15 | O59: =ROUNDUP((N59 - 3)*12.5 + 62.5,0) -> 213 | P59: =ROUND(J59+O59,0) -> 725 | Q59: =IF(I59 = "N/A","",ROUND(SUM(I59)-P59,0)) -> 7821 | R59: =R58+Q59 -> 71206 | S59: =IF(I329 = "N/A","0",R59-MAX($R$1:R59)) -> 0 | T59: =ROUND(AVERAGE(Q10:Q59),0) -> 763 | X59: 1200000
A60: 59 | B60: Friday | C60: 20 Jun 25 | I60: -4011 | J60: 664.75 | N60: 15 | O60: =ROUNDUP((N60 - 3)*12.5 + 62.5,0) -> 213 | P60: =ROUND(J60+O60,0) -> 878 | Q60: =IF(I60 = "N/A","",ROUND(SUM(I60)-P60,0)) -> -4889 | R60: =R59+Q60 -> 66317 | S60: =IF(I330 = "N/A","0",R60-MAX($R$1:R60)) -> -4889 | T60: =ROUND(AVERAGE(Q11:Q60),0) -> 645 | X60: 1200000
A61: 60 | B61: Monday | C61: 23 Jun 25 | I61: -12775.5 | J61: 768.96 | N61: 15 | O61: =ROUNDUP((N61 - 3)*12.5 + 62.5,0) -> 213 | P61: =ROUND(J61+O61,0) -> 982 | Q61: =IF(I61 = "N/A","",ROUND(SUM(I61)-P61,0)) -> -13758 | R61: =R60+Q61 -> 52559 | S61: =IF(I331 = "N/A","0",R61-MAX($R$1:R61)) -> -18647 | T61: =ROUND(AVERAGE(Q12:Q61),0) -> 252 | X61: 1200000
A62: 61 | B62: Tuesday | C62: 24 Jun 25 | I62: -51895 | J62: 1399.47 | N62: 15 | O62: =ROUNDUP((N62 - 3)*12.5 + 62.5,0) -> 213 | P62: =ROUND(J62+O62,0) -> 1612 | Q62: =IF(I62 = "N/A","",ROUND(SUM(I62)-P62,0)) -> -53507 | R62: =R61+Q62 -> -948 | S62: =IF(I332 = "N/A","0",R62-MAX($R$1:R62)) -> -72154 | T62: =ROUND(AVERAGE(Q13:Q62),0) -> -845 | X62: 1200000
A63: 62 | B63: Wednesday | C63: 25 Jun 25 | I63: 10497 | J63: 255.55 | N63: 15 | O63: =ROUNDUP((N63 - 3)*12.5 + 62.5,0) -> 213 | P63: =ROUND(J63+O63,0) -> 469 | Q63: =IF(I63 = "N/A","",ROUND(SUM(I63)-P63,0)) -> 10028 | R63: =R62+Q63 -> 9080 | S63: =IF(I333 = "N/A","0",R63-MAX($R$1:R63)) -> -62126 | T63: =ROUND(AVERAGE(Q14:Q63),0) -> -645 | X63: 1200000
A64: 63 | B64: Thursday | C64: 26 Jun 25 | I64: 1209 | J64: 1748.69 | N64: 15 | O64: =ROUNDUP((N64 - 3)*12.5 + 62.5,0) -> 213 | P64: =ROUND(J64+O64,0) -> 1962 | Q64: =IF(I64 = "N/A","",ROUND(SUM(I64)-P64,0)) -> -753 | R64: =R63+Q64 -> 8327 | S64: =IF(I334 = "N/A","0",R64-MAX($R$1:R64)) -> -62879 | T64: =ROUND(AVERAGE(Q15:Q64),0) -> -650 | X64: 1200000
... A74: 73 | B74: Thursday | C74: 10 Jul 25 | I74: 3502.5 | J74: 384.79 | N74: 9 | O74: =ROUNDUP((N74 - 3)*12.5 + 62.5,0) -> 138 | P74: =ROUND(J74+O74,0) -> 523 | Q74: =IF(I74 = "N/A","",ROUND(SUM(I74)-P74,0)) -> 2980 | R74: =R73+Q74 -> 69282 | S74: =IF(I344 = "N/A","0",R74-MAX($R$1:R74)) -> -1924 | T74: =ROUND(AVERAGE(Q25:Q74),0) -> 1517 | X74: 1200000
A75: 74 | B75: Friday | C75: 45849 | I75: -4667.75 | J75: 210 | N75: 12 | O75: =ROUNDUP((N75 - 3)*12.5 + 62.5,0) -> 175 | P75: =ROUND(J75+O75,0) -> 385 | Q75: =IF(I75 = "N/A","",ROUND(SUM(I75)-P75,0)) -> -5053 | R75: =R74+Q75 -> 64229 | S75: =IF(I345 = "N/A","0",R75-MAX($R$1:R75)) -> -6977 | T75: =ROUND(AVERAGE(Q26:Q75),0) -> 1494 | X75: 1200000
A76: 75 | B76: Monday | C76: 14 Jul 25 | I76: 1533.75 | J76: 159.23 | N76: 6 | O76: =ROUNDUP((N76 - 3)*12.5 + 62.5,0) -> 100 | P76: =ROUND(J76+O76,0) -> 259 | Q76: =IF(I76 = "N/A","",ROUND(SUM(I76)-P76,0)) -> 1275 | R76: =R75+Q76 -> 65504 | S76: =IF(I346 = "N/A","0",R76-MAX($R$1:R76)) -> -5702 | T76: =ROUND(AVERAGE(Q27:Q76),0) -> 1426 | X76: 1200000
A77: 76 | B77: Tuesday | C77: 15 Jul 25 | I77: 8876.25 | J77: 536.12 | N77: 6 | O77: =ROUNDUP((N77 - 3)*12.5 + 62.5,0) -> 100 | P77: =ROUND(J77+O77,0) -> 636 | Q77: =IF(I77 = "N/A","",ROUND(SUM(I77)-P77,0)) -> 8240 | R77: =R76+Q77 -> 73744 | S77: =IF(I347 = "N/A","0",R77-MAX($R$1:R77)) -> 0 | T77: =ROUND(AVERAGE(Q28:Q77),0) -> 1527 | X77: 1200000
A78: 77 | B78: Wednesday | C78: 16 Jul 25 | I78: -858.75 | J78: 130.61 | N78: 6 | O78: =ROUNDUP((N78 - 3)*12.5 + 62.5,0) -> 100 | P78: =ROUND(J78+O78,0) -> 231 | Q78: =IF(I78 = "N/A","",ROUND(SUM(I78)-P78,0)) -> -1090 | R78: =R77+Q78 -> 72654 | S78: =IF(I348 = "N/A","0",R78-MAX($R$1:R78)) -> -1090 | T78: =ROUND(AVERAGE(Q29:Q78),0) -> 1431 | X78: 1200000
A79: 78 | B79: Thursday | C79: 17 Jul 25 | I79: 10560 | J79: 265.95 | N79: 6 | O79: =ROUNDUP((N79 - 3)*12.5 + 62.5,0) -> 100 | P79: =ROUND(J79+O79,0) -> 366 | Q79: =IF(I79 = "N/A","",ROUND(SUM(I79)-P79,0)) -> 10194 | R79: =R78+Q79 -> 82848 | S79: =IF(I349 = "N/A","0",R79-MAX($R$1:R79)) -> 0 | T79: =ROUND(AVERAGE(Q30:Q79),0) -> 1683 | X79: 1200000
A80: 79 | B80: Friday | C80: 18 Jul 25 | I80: 3895.75 | J80: 472.18 | N80: 6 | O80: =ROUNDUP((N80 - 3)*12.5 + 62.5,0) -> 100 | P80: =ROUND(J80+O80,0) -> 572 | Q80: =IF(I80 = "N/A","",ROUND(SUM(I80)-P80,0)) -> 3324 | R80: =R79+Q80 -> 86172 | S80: =IF(I350 = "N/A","0",R80-MAX($R$1:R80)) -> 0 | T80: =ROUND(AVERAGE(Q31:Q80),0) -> 2046 | X80: 1200000
A81: 80 | B81: Monday | C81: 21 Jul 25 | I81: 2173 | J81: 271.63 | N81: 6 | O81: =ROUNDUP((N81 - 3)*12.5 + 62.5,0) -> 100 | P81: =ROUND(J81+O81,0) -> 372 | Q81: =IF(I81 = "N/A","",ROUND(SUM(I81)-P81,0)) -> 1801 | R81: =R80+Q81 -> 87973 | S81: =IF(I351 = "N/A","0",R81-MAX($R$1:R81)) -> 0 | T81: =ROUND(AVERAGE(Q32:Q81),0) -> 2059 | X81: 1200000
A82: 81 | B82: Tuesday | C82: 22 Jul 25 | I82: 10592.25 | J82: 529.53 | N82: 6 | O82: =ROUNDUP((N82 - 3)*12.5 + 62.5,0) -> 100 | P82: =ROUND(J82+O82,0) -> 630 | Q82: =IF(I82 = "N/A","",ROUND(SUM(I82)-P82,0)) -> 9962 | R82: =R81+Q82 -> 97935 | S82: =IF(I352 = "N/A","0",R82-MAX($R$1:R82)) -> 0 | T82: =ROUND(AVERAGE(Q33:Q82),0) -> 2162 | X82: 1200000
A83: 82 | B83: Wednesday | C83: 23 Jul 25 | I83: -4711.25 | J83: 313.28 | N83: 6 | O83: =ROUNDUP((N83 - 3)*12.5 + 62.5,0) -> 100 | P83: =ROUND(J83+O83,0) -> 413 | Q83: =IF(I83 = "N/A","",ROUND(SUM(I83)-P83,0)) -> -5124 | R83: =R82+Q83 -> 92811 | S83: =IF(I353 = "N/A","0",R83-MAX($R$1:R83)) -> -5124 | T83: =ROUND(AVERAGE(Q34:Q83),0) -> 2619 | X83: 1200000
A84: 83 | B84: Thursday | C84: 24 Jul 25 | I84: 8287.5 | J84: 621.6 | N84: 6 | O84: =ROUNDUP((N84 - 3)*12.5 + 62.5,0) -> 100 | P84: =ROUND(J84+O84,0) -> 722 | Q84: =IF(I84 = "N/A","",ROUND(SUM(I84)-P84,0)) -> 7566 | R84: =R83+Q84 -> 100377 | S84: =IF(I354 = "N/A","0",R84-MAX($R$1:R84)) -> 0 | T84: =ROUND(AVERAGE(Q35:Q84),0) -> 2581 | X84: 1200000
A85: 84 | B85: Friday | C85: 25 Jul 25 | I85: -5582.25 | J85: 901.33 | N85: 6 | O85: =ROUNDUP((N85 - 3)*12.5 + 62.5,0) -> 100 | P85: =ROUND(J85+O85,0) -> 1001 | Q85: =IF(I85 = "N/A","",ROUND(SUM(I85)-P85,0)) -> -6583 | R85: =R84+Q85 -> 93794 | S85: =IF(I355 = "N/A","0",R85-MAX($R$1:R85)) -> -6583 | T85: =ROUND(AVERAGE(Q36:Q85),0) -> 2318 | X85: 1200000
A86: 85 | B86: Monday | C86: 28 Jul 25 | I86: 3833.75 | J86: 462.64 | N86: 6 | O86: =ROUNDUP((N86 - 3)*12.5 + 62.5,0) -> 100 | P86: =ROUND(J86+O86,0) -> 563 | Q86: =IF(I86 = "N/A","",ROUND(SUM(I86)-P86,0)) -> 3271 | R86: =R85+Q86 -> 97065 | S86: =IF(I356 = "N/A","0",R86-MAX($R$1:R86)) -> -3312 | T86: =ROUND(AVERAGE(Q37:Q86),0) -> 2347 | X86: 1200000
A87: 86 | B87: Tuesday | C87: 29 Jul 25 | I87: -2855 | J87: 1307.22 | N87: 6 | O87: =ROUNDUP((N87 - 3)*12.5 + 62.5,0) -> 100 | P87: =ROUND(J87+O87,0) -> 1407 | Q87: =IF(I87 = "N/A","",ROUND(SUM(I87)-P87,0)) -> -4262 | R87: =R86+Q87 -> 92803 | S87: =IF(I357 = "N/A","0",R87-MAX($R$1:R87)) -> -7574 | T87: =ROUND(AVERAGE(Q38:Q87),0) -> 2289 | X87: 1200000
... A100: 99 | B100: Monday | C100: 18 Aug 25 | I100: 8672 | J100: 326.72 | N100: 6 | O100: =ROUNDUP((N100 - 3)*12.5 + 62.5,0) -> 100 | P100: =ROUND(J100+O100,0) -> 427 | Q100: =IF(I100 = "N/A","",ROUND(SUM(I100)-P100,0)) -> 8245 | R100: =R99+Q100 -> 80067 | S100: =IF(I370 = "N/A","0",R100-MAX($R$1:R100)) -> -20310 | T100: =ROUND(AVERAGE(Q51:Q100),0) -> 955 | X100: 1200000
A101: 100 | B101: Tuesday | C101: 19 Aug 25 | I101: 5458.75 | J101: 371.08 | N101: 6 | O101: =ROUNDUP((N101 - 3)*12.5 + 62.5,0) -> 100 | P101: =ROUND(J101+O101,0) -> 471 | Q101: =IF(I101 = "N/A","",ROUND(SUM(I101)-P101,0)) -> 4988 | R101: =R100+Q101 -> 85055 | S101: =IF(I371 = "N/A","0",R101-MAX($R$1:R101)) -> -15322 | T101: =ROUND(AVERAGE(Q52:Q101),0) -> 888 | U101: =ROUND(AVERAGE(Q2:Q101),0) -> 886 | V101: =ROUND(AVERAGE(P2:P101),0) -> 791 | W101: =ROUND(V101*100/U101,1) -> 89.3 | X101: 1200000 | Y101: =AVERAGE(X2:X101) -> 1200000 | Z101: =ROUND(U101*100*100/Y101,0) -> 7
A102: 101 | B102: Wednesday | C102: 20 Aug 25 | I102: -7556.25 | J102: 724.18 | N102: 6 | O102: =ROUNDUP((N102 - 3)*12.5 + 62.5,0) -> 100 | P102: =ROUND(J102+O102,0) -> 824 | Q102: =IF(I102 = "N/A","",ROUND(SUM(I102)-P102,0)) -> -8380 | R102: =R101+Q102 -> 76675 | S102: =IF(I372 = "N/A","0",R102-MAX($R$1:R102)) -> -23702 | T102: =ROUND(AVERAGE(Q53:Q102),0) -> 331 | U102: =ROUND(AVERAGE(Q3:Q102),0) -> 790 | V102: =ROUND(AVERAGE(P3:P102),0) -> 791 | W102: =ROUND(V102*100/U102,1) -> 100.1 | X102: 1200000 | Y102: =AVERAGE(X3:X102) -> 1200000 | Z102: =ROUND(U102*100*100/Y102,0) -> 7
A103: 102 | B103: Thursday | C103: 21 Aug 25 | I103: 10822.5 | J103: 620.12 | N103: 6 | O103: =ROUNDUP((N103 - 3)*12.5 + 62.5,0) -> 100 | P103: =ROUND(J103+O103,0) -> 720 | Q103: =IF(I103 = "N/A","",ROUND(SUM(I103)-P103,0)) -> 10103 | R103: =R102+Q103 -> 86778 | S103: =IF(I373 = "N/A","0",R103-MAX($R$1:R103)) -> -13599 | T103: =ROUND(AVERAGE(Q54:Q103),0) -> 601 | U103: =ROUND(AVERAGE(Q4:Q103),0) -> 936 | V103: =ROUND(AVERAGE(P4:P103),0) -> 779 | W103: =ROUND(V103*100/U103,1) -> 83.2 | X103: 1200000 | Y103: =AVERAGE(X4:X103) -> 1200000 | Z103: =ROUND(U103*100*100/Y103,0) -> 8
A104: 103 | B104: Friday | C104: 22 Aug 25 | I104: 6911.25 | J104: 694.74 | N104: 6 | O104: =ROUNDUP((N104 - 3)*12.5 + 62.5,0) -> 100 | P104: =ROUND(J104+O104,0) -> 795 | Q104: =IF(I104 = "N/A","",ROUND(SUM(I104)-P104,0)) -> 6116 | R104: =R103+Q104 -> 92894 | S104: =IF(I374 = "N/A","0",R104-MAX($R$1:R104)) -> -7483 | T104: =ROUND(AVERAGE(Q55:Q104),0) -> 849 | U104: =ROUND(AVERAGE(Q5:Q104),0) -> 937 | V104: =ROUND(AVERAGE(P5:P104),0) -> 782 | W104: =ROUND(V104*100/U104,1) -> 83.5 | X104: 1200000 | Y104: =AVERAGE(X5:X104) -> 1200000 | Z104: =ROUND(U104*100*100/Y104,0) -> 8
A105: 104 | B105: Monday | C105: 25 Aug 25 | I105: 4089 | J105: 333.16 | N105: 6 | O105: =ROUNDUP((N105 - 3)*12.5 + 62.5,0) -> 100 | P105: =ROUND(J105+O105,0) -> 433 | Q105: =IF(I105 = "N/A","",ROUND(SUM(I105)-P105,0)) -> 3656 | R105: =R104+Q105 -> 96550 | S105: =IF(I375 = "N/A","0",R105-MAX($R$1:R105)) -> -3827 | T105: =ROUND(AVERAGE(Q56:Q105),0) -> 906 | U105: =ROUND(AVERAGE(Q6:Q105),0) -> 868 | V105: =ROUND(AVERAGE(P6:P105),0) -> 784 | W105: =ROUND(V105*100/U105,1) -> 90.3 | X105: 1200000 | Y105: =AVERAGE(X6:X105) -> 1200000 | Z105: =ROUND(U105*100*100/Y105,0) -> 7
A106: 105 | B106: Tuesday | C106: 26 Aug 25 | I106: 434.25 | J106: 863.01 | N106: 6 | O106: =ROUNDUP((N106 - 3)*12.5 + 62.5,0) -> 100 | P106: =ROUND(J106+O106,0) -> 963 | Q106: =IF(I106 = "N/A","",ROUND(SUM(I106)-P106,0)) -> -529 | R106: =R105+Q106 -> 96021 | S106: =IF(I376 = "N/A","0",R106-MAX($R$1:R106)) -> -4356 | T106: =ROUND(AVERAGE(Q57:Q106),0) -> 1031 | U106: =ROUND(AVERAGE(Q7:Q106),0) -> 777 | V106: =ROUND(AVERAGE(P7:P106),0) -> 790 | W106: =ROUND(V106*100/U106,1) -> 101.7 | X106: 1200000 | Y106: =AVERAGE(X7:X106) -> 1200000 | Z106: =ROUND(U106*100*100/Y106,0) -> 6
A107: 106 | B107: Thursday | C107: 28 Aug 25 | I107: -1478.25 | J107: 1587.27 | N107: 6 | O107: =ROUNDUP((N107 - 3)*12.5 + 62.5,0) -> 100 | P107: =ROUND(J107+O107,0) -> 1687 | Q107: =IF(I107 = "N/A","",ROUND(SUM(I107)-P107,0)) -> -3165 | R107: =R106+Q107 -> 92856 | S107: =IF(I377 = "N/A","0",R107-MAX($R$1:R107)) -> -7521 | T107: =ROUND(AVERAGE(Q58:Q107),0) -> 640 | U107: =ROUND(AVERAGE(Q8:Q107),0) -> 774 | V107: =ROUND(AVERAGE(P8:P107),0) -> 774 | W107: =ROUND(V107*100/U107,1) -> 100 | X107: 1200000 | Y107: =AVERAGE(X8:X107) -> 1200000 | Z107: =ROUND(U107*100*100/Y107,0) -> 6
A108: 107 | B108: Friday | C108: 29 Aug 25 | I108: 10496.25 | J108: 164.8 | N108: 6 | O108: =ROUNDUP((N108 - 3)*12.5 + 62.5,0) -> 100 | P108: =ROUND(F108+J108+O108,0) -> 265 | Q108: =IF(I108 = "N/A","",ROUND(SUM(D108+I108)-P108,0)) -> 10231 | R108: =R107+Q108 -> 103087 | S108: =IF(I378 = "N/A","0",R108-MAX($R$1:R108)) -> 0 | T108: =ROUND(AVERAGE(Q59:Q108),0) -> 794 | U108: =ROUND(AVERAGE(Q9:Q108),0) -> 838 | V108: =ROUND(AVERAGE(P9:P108),0) -> 759 | W108: =ROUND(V108*100/U108,1) -> 90.6 | X108: 1200000 | Y108: =AVERAGE(X9:X108) -> 1200000 | Z108: =ROUND(U108*100*100/Y108,0) -> 7
A109: 108 | B109: Monday | C109: 1 Sept 25 | D109: 651.25 | F109: 23.15 | I109: -1710 | J109: 121.83 | N109: 6 | O109: =ROUNDUP((N109 - 3)*12.5 + 62.5,0) -> 100 | P109: =ROUND(F109+J109+O109,0) -> 245 | Q109: =IF(I109 = "N/A","",ROUND(SUM(D109+I109)-P109,0)) -> -1304 | R109: =R108+Q109 -> 101783 | S109: =IF(I379 = "N/A","0",R109-MAX($R$1:R109)) -> -1304 | T109: =ROUND(AVERAGE(Q60:Q109),0) -> 612 | U109: =ROUND(AVERAGE(Q10:Q109),0) -> 685 | V109: =ROUND(AVERAGE(P10:P109),0) -> 759 | W109: =ROUND(V109*100/U109,1) -> 110.8 | X109: 1200000 | Y109: =AVERAGE(X10:X109) -> 1200000 | Z109: =ROUND(U109*100*100/Y109,0) -> 6
A110: 109 | B110: Tuesday | C110: 2 Sept 25 | D110: 690 | F110: 361.94 | I110: 857.5 | J110: 738.94 | N110: 6 | O110: =ROUNDUP((N110 - 3)*12.5 + 62.5,0) -> 100 | P110: =ROUND(F110+J110+O110,0) -> 1201 | Q110: =IF(I110 = "N/A","",ROUND(SUM(D110+I110)-P110,0)) -> 347 | R110: =R109+Q110 -> 102130 | S110: =IF(I380 = "N/A","0",R110-MAX($R$1:R110)) -> -957 | T110: =ROUND(AVERAGE(Q61:Q110),0) -> 716 | U110: =ROUND(AVERAGE(Q11:Q110),0) -> 681 | V110: =ROUND(AVERAGE(P11:P110),0) -> 770 | W110: =ROUND(V110*100/U110,1) -> 113.1 | X110: 1200000 | Y110: =AVERAGE(X11:X110) -> 1200000 | Z110: =ROUND(U110*100*100/Y110,0) -> 6
A111: 110 | B111: Wednesday | C111: 3 Sept 25 | D111: -2590 | F111: 492.45 | I111: 648.75 | J111: 311.96 | N111: 6 | O111: =ROUNDUP((N111 - 3)*12.5 + 62.5,0) -> 100 | P111: =ROUND(F111+J111+O111,0) -> 904 | Q111: =IF(I111 = "N/A","",ROUND(SUM(D111+I111)-P111,0)) -> -2845 | R111: =R110+Q111 -> 99285 | S111: =IF(I381 = "N/A","0",R111-MAX($R$1:R111)) -> -3802 | T111: =ROUND(AVERAGE(Q62:Q111),0) -> 935 | U111: =ROUND(AVERAGE(Q12:Q111),0) -> 600 | V111: =ROUND(AVERAGE(P12:P111),0) -> 768 | W111: =ROUND(V111*100/U111,1) -> 128 | X111: 1200000 | Y111: =AVERAGE(X12:X111) -> 1200000 | Z111: =ROUND(U111*100*100/Y111,0) -> 5
A112: 111 | B112: Thursday | C112: 4 Sept 25 | D112: -2885 | F112: 996.85 | I112: 858 | J112: 432.01 | N112: 6 | O112: =ROUNDUP((N112 - 3)*12.5 + 62.5,0) -> 100 | P112: =ROUND(F112+J112+O112,0) -> 1529 | Q112: =IF(I112 = "N/A","",ROUND(SUM(D112+I112)-P112,0)) -> -3556 | R112: =R111+Q112 -> 95729 | S112: =IF(I382 = "N/A","0",R112-MAX($R$1:R112)) -> -7358 | T112: =ROUND(AVERAGE(Q63:Q112),0) -> 1934 | U112: =ROUND(AVERAGE(Q13:Q112),0) -> 558 | V112: =ROUND(AVERAGE(P13:P112),0) -> 782 | W112: =ROUND(V112*100/U112,1) -> 140.1 | X112: 1200000 | Y112: =AVERAGE(X13:X112) -> 1200000 | Z112: =ROUND(U112*100*100/Y112,0) -> 5
A113: 112 | B113: Friday | C113: 5 Sept 25 | D113: 4932.5 | F113: 496.03 | I113: 731.25 | J113: 242.35 | N113: 6 | O113: =ROUNDUP((N113 - 3)*12.5 + 62.5,0) -> 100 | P113: =ROUND(F113+J113+O113,0) -> 838 | Q113: =IF(I113 = "N/A","",ROUND(SUM(D113+I113)-P113,0)) -> 4826 | R113: =R112+Q113 -> 100555 | S113: =IF(I383 = "N/A","0",R113-MAX($R$1:R113)) -> -2532 | T113: =ROUND(AVERAGE(Q64:Q113),0) -> 1830 | U113: =ROUND(AVERAGE(Q14:Q113),0) -> 605 | V113: =ROUND(AVERAGE(P14:P113),0) -> 787 | W113: =ROUND(V113*100/U113,1) -> 130.1 | X113: 1200000 | Y113: =AVERAGE(X14:X113) -> 1200000 | Z113: =ROUND(U113*100*100/Y113,0) -> 5
A114: 113 | B114: Monday | C114: 8 Sept 25 | D114: -2675 | F114: 994.35 | I114: 2710.5 | J114: 470.15 | N114: 6 | O114: =ROUNDUP((N114 - 3)*12.5 + 62.5,0) -> 100 | P114: =ROUND(F114+J114+O114,0) -> 1565 | Q114: =IF(I114 = "N/A","",ROUND(SUM(D114+I114)-P114,0)) -> -1530 | R114: =R113+Q114 -> 99025 | S114: =IF(I384 = "N/A","0",R114-MAX($R$1:R114)) -> -4062 | T114: =ROUND(AVERAGE(Q65:Q114),0) -> 1814 | U114: =ROUND(AVERAGE(Q15:Q114),0) -> 594 | V114: =ROUND(AVERAGE(P15:P114),0) -> 797 | W114: =ROUND(V114*100/U114,1) -> 134.2 | X114: 1200000 | Y114: =AVERAGE(X15:X114) -> 1200000 | Z114: =ROUND(U114*100*100/Y114,0) -> 5
A115: 114 | B115: Tuesday | C115: 9 Sept 25 | D115: -2285 | F115: 995.75 | I115: 11096.25 | J115: 325.12 | N115: 6 | O115: =ROUNDUP((N115 - 3)*12.5 + 62.5,0) -> 100 | P115: =ROUND(F115+J115+O115,0) -> 1421 | Q115: =IF(I115 = "N/A","",ROUND(SUM(D115+I115)-P115,0)) -> 7390 | R115: =R114+Q115 -> 106415 | S115: =IF(I385 = "N/A","0",R115-MAX($R$1:R115)) -> 0 | T115: =ROUND(AVERAGE(Q66:Q115),0) -> 1693 | U115: =ROUND(AVERAGE(Q16:Q115),0) -> 802 | V115: =ROUND(AVERAGE(P16:P115),0) -> 810 | W115: =ROUND(V115*100/U115,1) -> 101 | X115: 1200000 | Y115: =AVERAGE(X16:X115) -> 1200000 | Z115: =ROUND(U115*100*100/Y115,0) -> 7
A116: 115 | B116: Wednesday | C116: 10 Sept 25 | D116: 1398.75 | F116: 62.77 | I116: 6770 | J116: 139.05 | N116: 6 | O116: =ROUNDUP((N116 - 3)*12.5 + 62.5,0) -> 100 | P116: =ROUND(F116+J116+O116,0) -> 302 | Q116: =IF(I116 = "N/A","",ROUND(SUM(D116+I116)-P116,0)) -> 7867 | R116: =R115+Q116 -> 114282 | S116: =IF(I386 = "N/A","0",R116-MAX($R$1:R116)) -> 0 | T116: =ROUND(AVERAGE(Q67:Q116),0) -> 1821 | U116: =ROUND(AVERAGE(Q17:Q116),0) -> 826 | V116: =ROUND(AVERAGE(P17:P116),0) -> 809 | W116: =ROUND(V116*100/U116,1) -> 97.9 | X116: 1200000 | Y116: =AVERAGE(X17:X116) -> 1200000 | Z116: =ROUND(U116*100*100/Y116,0) -> 7
A117: 116 | B117: Thursday | C117: 11 Sept 25 | D117: 1348.75 | F117: 25.33 | I117: 12458.5 | J117: 79.27 | N117: 6 | O117: =ROUNDUP((N117 - 3)*12.5 + 62.5,0) -> 100 | P117: =ROUND(F117+J117+O117,0) -> 205 | Q117: =IF(I117 = "N/A","",ROUND(SUM(D117+I117)-P117,0)) -> 13602 | R117: =R116+Q117 -> 127884 | S117: =IF(I387 = "N/A","0",R117-MAX($R$1:R117)) -> 0 | T117: =ROUND(AVERAGE(Q68:Q117),0) -> 1729 | U117: =ROUND(AVERAGE(Q18:Q117),0) -> 954 | V117: =ROUND(AVERAGE(P18:P117),0) -> 807 | W117: =ROUND(V117*100/U117,1) -> 84.6 | X117: 1200000 | Y117: =AVERAGE(X18:X117) -> 1200000 | Z117: =ROUND(U117*100*100/Y117,0) -> 8
A118: 117 | B118: Friday | C118: 12 Sept 25 | D118: 0 | F118: 0 | I118: -2391.25 | J118: 229.96 | N118: 6 | O118: =ROUNDUP((N118 - 3)*12.5 + 62.5,0) -> 100 | P118: =ROUND(F118+J118+O118,0) -> 330 | Q118: =IF(I118 = "N/A","",ROUND(SUM(D118+I118)-P118,0)) -> -2721 | R118: =R117+Q118 -> 125163 | S118: =IF(I388 = "N/A","0",R118-MAX($R$1:R118)) -> -2721 | T118: =ROUND(AVERAGE(Q69:Q118),0) -> 1637 | U118: =ROUND(AVERAGE(Q19:Q118),0) -> 913 | V118: =ROUND(AVERAGE(P19:P118),0) -> 779 | W118: =ROUND(V118*100/U118,1) -> 85.3 | X118: 1200000 | Y118: =AVERAGE(X19:X118) -> 1200000 | Z118: =ROUND(U118*100*100/Y118,0) -> 8
A119: 118 | B119: Monday | C119: 15 Sept 25 | D119: 0 | F119: 0 | I119: 6158.75 | J119: 66.57 | N119: 6 | O119: =ROUNDUP((N119 - 3)*12.5 + 62.5,0) -> 100 | P119: =ROUND(F119+J119+O119,0) -> 167 | Q119: =IF(I119 = "N/A","",ROUND(SUM(D119+I119)-P119,0)) -> 5992 | R119: =R118+Q119 -> 131155 | S119: =IF(I389 = "N/A","0",R119-MAX($R$1:R119)) -> 0 | T119: =ROUND(AVERAGE(Q70:Q119),0) -> 1748 | U119: =ROUND(AVERAGE(Q20:Q119),0) -> 1115 | V119: =ROUND(AVERAGE(P20:P119),0) -> 768 | W119: =ROUND(V119*100/U119,1) -> 68.9 | X119: 1200000 | Y119: =AVERAGE(X20:X119) -> 1200000 | Z119: =ROUND(U119*100*100/Y119,0) -> 9
A120: 119 | B120: Tuesday | C120: 16 Sept 25 | D120: 0 | F120: 0 | I120: 5495 | J120: 215.27 | N120: 6 | O120: =ROUNDUP((N120 - 3)*12.5 + 62.5,0) -> 100 | P120: =ROUND(F120+J120+O120,0) -> 315 | Q120: =IF(I120 = "N/A","",ROUND(SUM(D120+I120)-P120,0)) -> 5180 | R120: =R119+Q120 -> 136335 | S120: =IF(I390 = "N/A","0",R120-MAX($R$1:R120)) -> 0 | T120: =ROUND(AVERAGE(Q71:Q120),0) -> 1767 | U120: =ROUND(AVERAGE(Q21:Q120),0) -> 1338 | V120: =ROUND(AVERAGE(P21:P120),0) -> 770 | W120: =ROUND(V120*100/U120,1) -> 57.5 | X120: 1200000 | Y120: =AVERAGE(X21:X120) -> 1200000 | Z120: =ROUND(U120*100*100/Y120,0) -> 11
... A271: 270 | B271: Thursday | C271: 30 Apr 26 | D271: 0 | F271: 0 | I271: 12261.5 | J271: 1062.64 | N271: 14 | O271: =ROUNDUP((N271 - 3)*12.5 + 62.5,0) -> 200 | P271: =ROUND(F271+J271+O271,0) -> 1263 | Q271: =IF(I271 = "N/A","",ROUND(SUM(D271+I271)-P271,0)) -> 10999 | R271: =R270+Q271 -> 289483 | S271: =IF(I541 = "N/A","0",R271-MAX($R$1:R271)) -> -43838 | T271: =ROUND(AVERAGE(Q222:Q271),0) -> -738 | U271: =ROUND(AVERAGE(Q172:Q271),0) -> 947 | V271: =ROUND(AVERAGE(P172:P271),0) -> 660 | W271: =ROUND(V271*100/U271,1) -> 69.7 | X271: 1200000 | Y271: =AVERAGE(X172:X271) -> 1200000 | Z271: =ROUND(U271*100*100/Y271,0) -> 8
A272: 271 | B272: Monday | C272: 4 May 26 | D272: -811 | E272: 100 | F272: 327.88 | G272: 427.88 | H272: -1038.88 | I272: -1260.75 | J272: 320 | K272: 209.51 | L272: 529.51 | M272: -1150.26 | N272: 14 | O272: =ROUNDUP((N272 - 3)*12.5 + 62.5,0) -> 200 | P272: =ROUND(F272+J272+O272,0) -> 848 | Q272: =IF(I272 = "N/A","",ROUND(SUM(D272+I272)-P272,0)) -> -2920 | R272: =R271+Q272 -> 286563 | S272: =IF(I542 = "N/A","0",R272-MAX($R$1:R272)) -> -46758 | T272: =ROUND(AVERAGE(Q223:Q272),0) -> -931 | U272: =ROUND(AVERAGE(Q173:Q272),0) -> 849 | V272: =ROUND(AVERAGE(P173:P272),0) -> 666 | W272: =ROUND(V272*100/U272,1) -> 78.4 | X272: 1200000 | Y272: =AVERAGE(X173:X272) -> 1200000 | Z272: =ROUND(U272*100*100/Y272,0) -> 7
A273: 272 | B273: Tuesday | C273: 5 May 26 | D273: 1920.5 | E273: 200 | F273: 332.32 | G273: 532.32 | H273: -1038.88 | I273: 353.5 | J273: 240 | K273: 120.4 | L273: 360.4 | M273: -1150.26 | N273: 14 | O273: =ROUNDUP((N273 - 3)*12.5 + 62.5,0) -> 200 | P273: =ROUND(F273+J273+O273,0) -> 772 | Q273: =IF(I273 = "N/A","",ROUND(SUM(D273+I273)-P273,0)) -> 1502 | R273: =R272+Q273 -> 288065 | S273: =IF(I543 = "N/A","0",R273-MAX($R$1:R273)) -> -45256 | T273: =ROUND(AVERAGE(Q224:Q273),0) -> -596 | U273: =ROUND(AVERAGE(Q174:Q273),0) -> 833 | V273: =ROUND(AVERAGE(P174:P273),0) -> 672 | W273: =ROUND(V273*100/U273,1) -> 80.7 | X273: 1200000 | Y273: =AVERAGE(X174:X273) -> 1200000 | Z273: =ROUND(U273*100*100/Y273,0) -> 7
A274: 273 | B274: Wednesday | C274: 6 May 26 | D274: -6063 | E274: 80 | F274: 303.59 | G274: 383.59 | H274: -1038.88 | I274: 0 | J274: 0 | K274: 0 | L274: 0 | M274: -1150.26 | N274: 14 | O274: =ROUNDUP((N274 - 3)*12.5 + 62.5,0) -> 200 | P274: =ROUND(F274+J274+O274,0) -> 504 | Q274: =IF(I274 = "N/A","",ROUND(SUM(D274+I274)-P274,0)) -> -6567 | R274: =R273+Q274 -> 281498 | S274: =IF(I544 = "N/A","0",R274-MAX($R$1:R274)) -> -51823 | T274: =ROUND(AVERAGE(Q225:Q274),0) -> -689 | U274: =ROUND(AVERAGE(Q175:Q274),0) -> 768 | V274: =ROUND(AVERAGE(P175:P274),0) -> 673 | W274: =ROUND(V274*100/U274,1) -> 87.6 | X274: 1200000 | Y274: =AVERAGE(X175:X274) -> 1200000 | Z274: =ROUND(U274*100*100/Y274,0) -> 6
A275: 274 | B275: Thursday | C275: 7 May 26 | D275: 138 | E275: 190 | F275: 319.37 | G275: 509.37 | H275: -1038.88 | I275: 5286.5 | J275: 640 | K275: 400.91 | L275: 1040.91 | M275: -1150.26 | N275: 14 | O275: =ROUNDUP((N275 - 3)*12.5 + 62.5,0) -> 200 | P275: =ROUND(F275+J275+O275,0) -> 1159 | Q275: =IF(I275 = "N/A","",ROUND(SUM(D275+I275)-P275,0)) -> 4266 | R275: =R274+Q275 -> 285764 | S275: =IF(I545 = "N/A","0",R275-MAX($R$1:R275)) -> -47557 | T275: =ROUND(AVERAGE(Q226:Q275),0) -> -586 | U275: =ROUND(AVERAGE(Q176:Q275),0) -> 813 | V275: =ROUND(AVERAGE(P176:P275),0) -> 679 | W275: =ROUND(V275*100/U275,1) -> 83.5 | X275: 1200000 | Y275: =AVERAGE(X176:X275) -> 1200000 | Z275: =ROUND(U275*100*100/Y275,0) -> 7
A276: 275 | B276: Friday | C276: 8 May 26 | D276: 2715.5 | E276: 30 | F276: 170 | G276: 200 | H276: -1038.88 | I276: 2056.5 | J276: 80 | K276: 49.42 | L276: 129.42 | M276: -1150.26 | N276: 14 | O276: =ROUNDUP((N276 - 3)*12.5 + 62.5,0) -> 200 | P276: =ROUND(F276+J276+O276,0) -> 450 | Q276: =IF(I276 = "N/A","",ROUND(SUM(D276+I276)-P276,0)) -> 4322 | R276: =R275+Q276 -> 290086 | S276: =IF(I546 = "N/A","0",R276-MAX($R$1:R276)) -> -43235 | T276: =ROUND(AVERAGE(Q227:Q276),0) -> -514 | U276: =ROUND(AVERAGE(Q177:Q276),0) -> 857 | V276: =ROUND(AVERAGE(P177:P276),0) -> 682 | W276: =ROUND(V276*100/U276,1) -> 79.6 | X276: 1200000 | Y276: =AVERAGE(X177:X276) -> 1200000 | Z276: =ROUND(U276*100*100/Y276,0) -> 7
A277: 276 | B277: Monday | C277: 11 May 26 | D277: 7497 | E277: 80 | F277: 147.39 | G277: 227.39 | H277: -1038.88 | I277: 3536.5 | J277: 160 | K277: 107.94 | L277: 267.94 | M277: -1150.26 | N277: 14 | O277: =ROUNDUP((N277 - 3)*12.5 + 62.5,0) -> 200 | P277: =ROUND(F277+J277+O277,0) -> 507 | Q277: =IF(I277 = "N/A","",ROUND(SUM(D277+I277)-P277,0)) -> 10527 | R277: =R276+Q277 -> 300613 | S277: =IF(I547 = "N/A","0",R277-MAX($R$1:R277)) -> -32708 | T277: =ROUND(AVERAGE(Q228:Q277),0) -> -140 | U277: =ROUND(AVERAGE(Q178:Q277),0) -> 892 | V277: =ROUND(AVERAGE(P178:P277),0) -> 680 | W277: =ROUND(V277*100/U277,1) -> 76.2 | X277: 1200000 | Y277: =AVERAGE(X178:X277) -> 1200000 | Z277: =ROUND(U277*100*100/Y277,0) -> 7
A278: 277 | B278: Tuesday | C278: 12 May 26 | D278: -4284.75 | E278: 310 | F278: 669.99 | G278: 979.99 | H278: -1038.88 | I278: 0 | J278: 0 | K278: 0 | L278: 0 | M278: -1150.26 | N278: 14 | O278: =ROUNDUP((N278 - 3)*12.5 + 62.5,0) -> 200 | P278: =ROUND(F278+J278+O278,0) -> 870 | Q278: =IF(I278 = "N/A","",ROUND(SUM(D278+I278)-P278,0)) -> -5155 | R278: =R277+Q278 -> 295458 | S278: =IF(I548 = "N/A","0",R278-MAX($R$1:R278)) -> -37863 | T278: =ROUND(AVERAGE(Q229:Q278),0) -> -157 | U278: =ROUND(AVERAGE(Q179:Q278),0) -> 875 | V278: =ROUND(AVERAGE(P179:P278),0) -> 685 | W278: =ROUND(V278*100/U278,1) -> 78.3 | X278: 1200000 | Y278: =AVERAGE(X179:X278) -> 1200000 | Z278: =ROUND(U278*100*100/Y278,0) -> 7
A279: 278 | B279: Wednesday | C279: 13 May 26 | D279: -3984 | E279: 50 | F279: 135.02 | G279: 185.02 | H279: -1038.88 | I279: -6888.69 | J279: 520 | K279: 793.71 | L279: 1313.71 | M279: -1150.26 | N279: 14 | O279: =ROUNDUP((N279 - 3)*12.5 + 62.5,0) -> 200 | P279: =ROUND(F279+J279+O279,0) -> 855 | Q279: =IF(I279 = "N/A","",ROUND(SUM(D279+I279)-P279,0)) -> -11728 | R279: =R278+Q279 -> 283730 | S279: =IF(I549 = "N/A","0",R279-MAX($R$1:R279)) -> -49591 | T279: =ROUND(AVERAGE(Q230:Q279),0) -> -517 | U279: =ROUND(AVERAGE(Q180:Q279),0) -> 766 | V279: =ROUND(AVERAGE(P180:P279),0) -> 691 | W279: =ROUND(V279*100/U279,1) -> 90.2 | X279: 1200000 | Y279: =AVERAGE(X180:X279) -> 1200000 | Z279: =ROUND(U279*100*100/Y279,0) -> 6
A280: 279 | B280: Thursday | C280: 14 May 26 | D280: -1672.75 | E280: 180 | F280: 240.35 | G280: 420.35 | H280: -1038.88 | I280: 4148 | J280: 200 | K280: 70.43 | L280: 270.43 | M280: -1150.26 | N280: 14 | O280: =ROUNDUP((N280 - 3)*12.5 + 62.5,0) -> 200 | P280: =ROUND(F280+J280+O280,0) -> 640 | Q280: =IF(I280 = "N/A","",ROUND(SUM(D280+I280)-P280,0)) -> 1835 | R280: =R279+Q280 -> 285565 | S280: =IF(I550 = "N/A","0",R280-MAX($R$1:R280)) -> -47756 | T280: =ROUND(AVERAGE(Q231:Q280),0) -> -581 | U280: =ROUND(AVERAGE(Q181:Q280),0) -> 703 | V280: =ROUND(AVERAGE(P181:P280),0) -> 694 | W280: =ROUND(V280*100/U280,1) -> 98.7 | X280: 1200000 | Y280: =AVERAGE(X181:X280) -> 1200000 | Z280: =ROUND(U280*100*100/Y280,0) -> 6
A281: 280 | B281: Friday | C281: 15 May 26 | D281: 4139.5 | E281: 20 | F281: 82.23 | G281: 102.23 | H281: -1038.88 | I281: 1432.5 | J281: 80 | K281: 53 | L281: 133 | M281: -1150.26 | N281: 14 | O281: =ROUNDUP((N281 - 3)*12.5 + 62.5,0) -> 200 | P281: =ROUND(F281+J281+O281,0) -> 362 | Q281: =IF(I281 = "N/A","",ROUND(SUM(D281+I281)-P281,0)) -> 5210 | R281: =R280+Q281 -> 290775 | S281: =IF(I551 = "N/A","0",R281-MAX($R$1:R281)) -> -42546 | T281: =ROUND(AVERAGE(Q232:Q281),0) -> -616 | U281: =ROUND(AVERAGE(Q182:Q281),0) -> 722 | V281: =ROUND(AVERAGE(P182:P281),0) -> 697 | W281: =ROUND(V281*100/U281,1) -> 96.5 | X281: 1200000 | Y281: =AVERAGE(X182:X281) -> 1200000 | Z281: =ROUND(U281*100*100/Y281,0) -> 6
A282: 281 | B282: Monday | C282: 18 May 26 | D282: 1857 | E282: 40 | F282: 159.54 | G282: 199.54 | H282: -1038.88 | I282: 0 | J282: 0 | K282: 0 | L282: 0 | M282: -1150.26 | N282: 14 | O282: =ROUNDUP((N282 - 3)*12.5 + 62.5,0) -> 200 | P282: =ROUND(F282+J282+O282,0) -> 360 | Q282: =IF(I282 = "N/A","",ROUND(SUM(D282+I282)-P282,0)) -> 1497 | R282: =R281+Q282 -> 292272 | S282: =IF(I552 = "N/A","0",R282-MAX($R$1:R282)) -> -41049 | T282: =ROUND(AVERAGE(Q233:Q282),0) -> -676 | U282: =ROUND(AVERAGE(Q183:Q282),0) -> 686 | V282: =ROUND(AVERAGE(P183:P282),0) -> 698 | W282: =ROUND(V282*100/U282,1) -> 101.7 | X282: 1200000 | Y282: =AVERAGE(X183:X282) -> 1200000 | Z282: =ROUND(U282*100*100/Y282,0) -> 6
...

Sheet Monthly returns 2025-26
B1: Monthly Gain | C1: Trading Gain | D1: Capital | E1: Trading gain in% | F1: Trading gain Avg 3 mnth
B2: 45748 | C2: =SUM('Trade Book'!Q3:Q23) -> -10152 | D2: 1200000 | E2: =IF(C2 ="N/A","", ROUND(C2*100/D2,2)) -> -0.85
B3: 45778 | C3: =SUM('Trade Book'!Q24:Q45) -> 27132 | D3: 1200000 | E3: =IF(C3 ="N/A","", ROUND(C3*100/D3,2)) -> 2.26
B4: 45809 | C4: =SUM('Trade Book'!Q46:Q66) -> 6250 | D4: 1200000 | E4: =IF(C4 ="N/A","", ROUND(C4*100/D4,2)) -> 0.52 | F4: =ROUND(AVERAGE(E2:E4),2) -> 0.64
B5: 45839 | C5: =SUM('Trade Book'!Q67:Q89) -> 25899 | D5: 1200000 | E5: =IF(C5 ="N/A","", ROUND(C5*100/D5,2)) -> 2.16 | F5: =ROUND(AVERAGE(E3:E5),2) -> 1.65
B6: 45870 | C6: =SUM('Trade Book'!Q90:Q108) -> 53958 | D6: 1200000 | E6: =IF(C6 ="N/A","", ROUND(C6*100/D6,2)) -> 4.5 | F6: =ROUND(AVERAGE(E4:E6),2) -> 2.39
B7: 45901 | C7: =SUM('Trade Book'!Q109:Q130) -> 64721 | D7: 1200000 | E7: =IF(C7 ="N/A","", ROUND(C7*100/D7,2)) -> 5.39 | F7: =ROUND(AVERAGE(E5:E7),2) -> 4.02
B8: 45931 | C8: =SUM('Trade Book'!Q131:Q150) -> 12296 | D8: 1200000 | E8: =IF(C8 ="N/A","", ROUND(C8*100/D8,2)) -> 1.02 | F8: =ROUND(AVERAGE(E6:E8),2) -> 3.64
B9: 45962 | C9: =SUM('Trade Book'!Q152:Q170) -> 18018 | D9: 1200000 | E9: =IF(C9 ="N/A","", ROUND(C9*100/D9,2)) -> 1.5 | F9: =ROUND(AVERAGE(E7:E9),2) -> 2.64
B10: 45992 | C10: =SUM('Trade Book'!Q171:Q192) -> 63457 | D10: 1200000 | E10: =IF(C10 ="N/A","", ROUND(C10*100/D10,2)) -> 5.29 | F10: =ROUND(AVERAGE(E8:E10),2) -> 2.6
B11: 46023 | C11: =SUM('Trade Book'!Q193:Q212) -> 610 | D11: 1200000 | E11: =IF(C11 ="N/A","", ROUND(C11*100/D11,2)) -> 0.05 | F11: =ROUND(AVERAGE(E9:E11),2) -> 2.28
B12: 46054 | C12: =SUM('Trade Book'!Q213:Q233) -> 66589 | D12: 1200000 | E12: =IF(C12 ="N/A","", ROUND(C12*100/D12,2)) -> 5.55 | F12: =ROUND(AVERAGE(E10:E12),2) -> 3.63
B13: 46082 | C13: =SUM('Trade Book'!Q234:Q252) -> -48592 | D13: 1200000 | E13: =IF(C13 ="N/A","", ROUND(C13*100/D13,2)) -> -4.05 | F13: =ROUND(AVERAGE(E11:E13),2) -> 0.52
B14: 46113 | C14: =SUM('Trade Book'!Q253:Q271) -> 8918 | D14: 1200000 | E14: =IF(C14 ="N/A","", ROUND(C14*100/D14,2)) -> 0.74 | F14: =ROUND(AVERAGE(E12:E14),2) -> 0.75
B15: 46143 | C15: =SUM('Trade Book'!Q272:Q289) -> 27144 | D15: 1200000 | E15: =IF(C15 ="N/A","", ROUND(C15*100/D15,2)) -> 2.26 | F15: =ROUND(AVERAGE(E13:E15),2) -> -0.35
A16: Total | C16: =SUM(C2:C14) -> 289104 | E16: =SUM(E2:E14) -> 24.08
D17: Average | E17: =ROUND(AVERAGE(E2:E13),1) -> 1.9
B20: Current Capital | C20: 1200000
B21: Percentage Trading gain in current capital | C21: =ROUND(C16*100/C20,1) -> 24.1

Sheet Daily Profit
